quantfinlib/__init__.py
quantfinlib/_datatypes/__init__.py
quantfinlib/_datatypes/timeseries.py
quantfinlib/clustering/__init__.py
quantfinlib/clustering/hierarchical.py
quantfinlib/clustering/metrics.py
quantfinlib/datasets/__init__.py
quantfinlib/datasets/_dataloader.py
quantfinlib/datasets/resources/daily_treasury_rates.csv.gz
quantfinlib/datasets/resources/multi_index_close.csv.gz
quantfinlib/datasets/resources/vix_ohlc.csv.gz
quantfinlib/distance/__init__.py
quantfinlib/distance/correlation.py
quantfinlib/distance/distance_matrix.py
quantfinlib/distance/information.py
quantfinlib/distance/matrix_divergence.py
quantfinlib/feature/__init__.py
quantfinlib/feature/indicators/__init__.py
quantfinlib/feature/indicators/_bands.py
quantfinlib/feature/indicators/_base.py
quantfinlib/feature/indicators/_macd.py
quantfinlib/feature/indicators/_rsi.py
quantfinlib/feature/micro_structure/__init__.py
quantfinlib/feature/micro_structure/_price_sequences.py
quantfinlib/feature/micro_structure/_sequential_trade_models.py
quantfinlib/feature/micro_structure/_strategic_trade_models.py
quantfinlib/feature/structural_breaks/__init__.py
quantfinlib/feature/structural_breaks/cusumtest.py
quantfinlib/math/__init__.py
quantfinlib/math/cov.py
quantfinlib/sim/__init__.py
quantfinlib/sim/_base.py
quantfinlib/sim/_bm.py
quantfinlib/sim/_gbm.py
quantfinlib/sim/_ou.py
quantfinlib/sim/_quasi_random.py
quantfinlib/train_test_split/__init__.py
quantfinlib/train_test_split/_base.py
quantfinlib/train_test_split/_dtypes.py
quantfinlib/train_test_split/combinatorial_cv.py
quantfinlib/train_test_split/kfoldpe.py
quantfinlib/train_test_split/walk_forward.py
quantfinlib/util/__init__.py
quantfinlib/util/_custom_types.py
quantfinlib/util/_dtypes.py
quantfinlib/util/_fs_utils.py
quantfinlib/util/_logging.py
quantfinlib/util/_validate.py
quantfinlib-0.0.6.dist-info/LICENSE
quantfinlib-0.0.6.dist-info/METADATA
quantfinlib-0.0.6.dist-info/WHEEL
quantfinlib-0.0.6.dist-info/RECORD
