Metadata-Version: 2.1
Name: quantfinlib
Version: 0.0.6
Summary: Fundamental package for quantitative finance with Python.
Home-page: https://quantfinlib.org/
License: MIT
Keywords: quantitative finance,asset management,financial engineering
Author: Thijs van den Berg, Andrejs Fedjajevs, Mohammadjavad Vakili, Nathan de Vries
Maintainer: Thijs van den Berg
Maintainer-email: thijs@sitmo.com
Requires-Python: >=3.9,<4.0
Classifier: Development Status :: 1 - Planning
Classifier: Intended Audience :: Financial and Insurance Industry
Classifier: Intended Audience :: Information Technology
Classifier: Intended Audience :: Science/Research
Classifier: License :: OSI Approved
Classifier: License :: OSI Approved :: MIT License
Classifier: Operating System :: OS Independent
Classifier: Programming Language :: Python :: 3
Classifier: Programming Language :: Python :: 3.9
Classifier: Programming Language :: Python :: 3.10
Classifier: Programming Language :: Python :: 3.11
Classifier: Programming Language :: Python :: 3.12
Classifier: Programming Language :: Python :: 3.13
Classifier: Topic :: Office/Business
Classifier: Topic :: Office/Business :: Financial
Classifier: Topic :: Office/Business :: Financial :: Investment
Classifier: Topic :: Scientific/Engineering
Classifier: Topic :: Scientific/Engineering :: Mathematics
Requires-Dist: cvxpy (==1.5.3)
Requires-Dist: ipykernel (>=6.29.4,<7.0.0)
Requires-Dist: ipywidgets (>=8.1.3,<9.0.0)
Requires-Dist: matplotlib (>=3.9.0,<4.0.0)
Requires-Dist: numpy (>1.20)
Requires-Dist: pandas (>=2.2.2,<3.0.0)
Requires-Dist: plotly (>=5.22.0,<6.0.0)
Requires-Dist: pydantic (>=2.9.0,<3.0.0)
Requires-Dist: pyyaml (>=6.0.1,<7.0.0)
Requires-Dist: scikit-learn (>=1.5.0,<2.0.0)
Requires-Dist: scipy (==1.13.1)
Project-URL: Repository, https://github.com/quantfinlib/quantfinlib
